kadoa_sdk/__init__.py
kadoa_sdk/py.typed
kadoa_sdk/version.py
kadoa_sdk/client/__init__.py
kadoa_sdk/client/client.py
kadoa_sdk/client/crawler_domain.py
kadoa_sdk/client/models.py
kadoa_sdk/client/notification_domain.py
kadoa_sdk/client/wiring.py
kadoa_sdk/core/__init__.py
kadoa_sdk/core/core_acl.py
kadoa_sdk/core/events.py
kadoa_sdk/core/exceptions.py
kadoa_sdk/core/http.py
kadoa_sdk/core/logger.py
kadoa_sdk/core/pagination.py
kadoa_sdk/core/realtime.py
kadoa_sdk/core/settings.py
kadoa_sdk/core/utils.py
kadoa_sdk/core/version_check.py
kadoa_sdk/crawler/__init__.py
kadoa_sdk/crawler/crawler_acl.py
kadoa_sdk/crawler/crawler_config_service.py
kadoa_sdk/crawler/crawler_session_service.py
kadoa_sdk/extraction/__init__.py
kadoa_sdk/extraction/extraction_acl.py
kadoa_sdk/extraction/extraction_module.py
kadoa_sdk/extraction/types.py
kadoa_sdk/extraction/services/__init__.py
kadoa_sdk/extraction/services/data_fetcher_service.py
kadoa_sdk/extraction/services/entity_detector_service.py
kadoa_sdk/extraction/services/entity_resolver_service.py
kadoa_sdk/extraction/services/extraction_builder_service.py
kadoa_sdk/extraction/services/workflow_manager_service.py
kadoa_sdk/notifications/__init__.py
kadoa_sdk/notifications/notification_channels_service.py
kadoa_sdk/notifications/notification_settings_service.py
kadoa_sdk/notifications/notification_setup_service.py
kadoa_sdk/notifications/notifications_acl.py
kadoa_sdk/schemas/__init__.py
kadoa_sdk/schemas/schema_builder.py
kadoa_sdk/schemas/schemas_acl.py
kadoa_sdk/schemas/schemas_service.py
kadoa_sdk/user/__init__.py
kadoa_sdk/user/user_service.py
kadoa_sdk/validation/__init__.py
kadoa_sdk/validation/validation_acl.py
kadoa_sdk/validation/validation_core_service.py
kadoa_sdk/validation/validation_rules_service.py
kadoa_sdk/workflows/__init__.py
kadoa_sdk/workflows/workflows_core_service.py
openapi_client/__init__.py
openapi_client/api_client.py
openapi_client/api_response.py
openapi_client/configuration.py
kadoa_sdk-0.18.0.dist-info/METADATA
kadoa_sdk-0.18.0.dist-info/WHEEL
kadoa_sdk-0.18.0.dist-info/top_level.txt
kadoa_sdk-0.18.0.dist-info/RECORD
