Metadata-Version: 2.4
Name: kadoa_sdk
Version: 0.18.0
Summary: Official Kadoa SDK for Python - Web data extraction and automation
Author-email: Kadoa <support@kadoa.com>
License-Expression: MIT
Project-URL: Homepage, https://github.com/kadoa-org/kadoa-sdks
Project-URL: Repository, https://github.com/kadoa-org/kadoa-sdks.git
Project-URL: Documentation, https://docs.kadoa.com
Keywords: kadoa,api,sdk,client,python
Classifier: Development Status :: 4 - Beta
Classifier: Intended Audience :: Developers
Classifier: Programming Language :: Python :: 3
Classifier: Programming Language :: Python :: 3.12
Requires-Python: >=3.12
Requires-Dist: certifi
Requires-Dist: python-dateutil
Requires-Dist: python-dotenv
Requires-Dist: pydantic
Requires-Dist: pydantic-settings
Requires-Dist: urllib3
Requires-Dist: websockets
Requires-Dist: aiohttp
Requires-Dist: aiohttp-retry
Provides-Extra: dev
Requires-Dist: pytest; extra == "dev"
Requires-Dist: pytest-cov; extra == "dev"
Requires-Dist: pytest-timeout; extra == "dev"
Requires-Dist: pytest-asyncio; extra == "dev"
Requires-Dist: black; extra == "dev"
Requires-Dist: mypy; extra == "dev"
Requires-Dist: ruff; extra == "dev"
Requires-Dist: pip-audit; extra == "dev"
Provides-Extra: test
Requires-Dist: pytest; extra == "test"
Requires-Dist: pytest-cov; extra == "test"
Requires-Dist: pytest-timeout; extra == "test"
Requires-Dist: pytest-asyncio; extra == "test"
